README.rst
setup.py
script/gen_symkey.py
script/jwdecrypt.py
script/jwenc.py
script/jwk_create.py
script/jwk_export.py
script/jwkutil.py
script/peek.py
src/jwkest/PBKDF2.py
src/jwkest/__init__.py
src/jwkest/aes_gcm.py
src/jwkest/aes_key_wrap.py
src/jwkest/curves.py
src/jwkest/ecc.py
src/jwkest/elliptic.py
src/jwkest/extra.py
src/jwkest/jwe.py
src/jwkest/jwk.py
src/jwkest/jws.py
src/jwkest/jwt.py
src/pyjwkest.egg-info/PKG-INFO
src/pyjwkest.egg-info/SOURCES.txt
src/pyjwkest.egg-info/dependency_links.txt
src/pyjwkest.egg-info/not-zip-safe
src/pyjwkest.egg-info/pbr.json
src/pyjwkest.egg-info/requires.txt
src/pyjwkest.egg-info/top_level.txt