Metadata-Version: 1.1
Name: pyjwkest
Version: 1.1.3
Summary: Python implementation of JWT, JWE, JWS and JWK
Home-page: UNKNOWN
Author: Roland Hedberg
Author-email: roland.hedberg@adm.umu.se
License: Apache 2.0
Platform: UNKNOWN
Classifier: Development Status :: 4 - Beta
Classifier: License :: OSI Approved :: Apache Software License
Classifier: Topic :: Software Development :: Libraries :: Python Modules
Classifier: Programming Language :: Python :: 2.7
Classifier: Programming Language :: Python :: 3.4
